WomenZhendeYoulinghunma/Dockerfile
WomenZhendeYoulinghunma/README.md
WomenZhendeYoulinghunma/__init__.py
WomenZhendeYoulinghunma/__main__.py
WomenZhendeYoulinghunma/file.epub
WomenZhendeYoulinghunma/index.html
WomenZhendeYoulinghunma/css/__init__.py
WomenZhendeYoulinghunma/css/annotations.css
WomenZhendeYoulinghunma/css/main.css
WomenZhendeYoulinghunma/css/normalize.css
WomenZhendeYoulinghunma/css/popup.css
WomenZhendeYoulinghunma/font/__init__.py
WomenZhendeYoulinghunma/font/fontello.eot
WomenZhendeYoulinghunma/font/fontello.svg
WomenZhendeYoulinghunma/font/fontello.ttf
WomenZhendeYoulinghunma/font/fontello.woff
WomenZhendeYoulinghunma/img/__init__.py
WomenZhendeYoulinghunma/img/annotator-glyph-sprite.png
WomenZhendeYoulinghunma/img/annotator-icon-sprite.png
WomenZhendeYoulinghunma/img/apple-touch-icon.png
WomenZhendeYoulinghunma/img/cancelfullscreen.png
WomenZhendeYoulinghunma/img/close.png
WomenZhendeYoulinghunma/img/fullscreen.png
WomenZhendeYoulinghunma/img/loader.gif
WomenZhendeYoulinghunma/img/menu-icon.png
WomenZhendeYoulinghunma/img/save.png
WomenZhendeYoulinghunma/img/saved.png
WomenZhendeYoulinghunma/img/settings-s.png
WomenZhendeYoulinghunma/img/settings.png
WomenZhendeYoulinghunma/img/star.png
WomenZhendeYoulinghunma/js/__init__.py
WomenZhendeYoulinghunma/js/epub.js
WomenZhendeYoulinghunma/js/epub.min.js
WomenZhendeYoulinghunma/js/epub.min.map
WomenZhendeYoulinghunma/js/hooks.min.js
WomenZhendeYoulinghunma/js/hooks.min.map
WomenZhendeYoulinghunma/js/reader.js
WomenZhendeYoulinghunma/js/reader.js.map
WomenZhendeYoulinghunma/js/reader.min.js
WomenZhendeYoulinghunma/js/reader.min.map
WomenZhendeYoulinghunma/js/hooks/__init__.py
WomenZhendeYoulinghunma/js/hooks/extensions/__init__.py
WomenZhendeYoulinghunma/js/hooks/extensions/highlight.js
WomenZhendeYoulinghunma/js/libs/__init__.py
WomenZhendeYoulinghunma/js/libs/jquery.min.js
WomenZhendeYoulinghunma/js/libs/localforage.min.js
WomenZhendeYoulinghunma/js/libs/screenfull.js
women_zhende_youlinghunma-2022.10.3.0.dist-info/METADATA
women_zhende_youlinghunma-2022.10.3.0.dist-info/WHEEL
women_zhende_youlinghunma-2022.10.3.0.dist-info/entry_points.txt
women_zhende_youlinghunma-2022.10.3.0.dist-info/top_level.txt
women_zhende_youlinghunma-2022.10.3.0.dist-info/RECORD
